{"duration":590,"records":[{"duration":166,"stepId":"io.quarkus.deployment.console.ConsoleProcessor#setupConsole","started":"19:10:04.921","dependents":[147,146,181,145,150],"id":144,"thread":"build-36"},{"duration":165,"stepId":"io.quarkus.deployment.logging.LoggingResourceProcessor#logConsoleCommand","started":"19:10:04.910","dependents":[192],"id":139,"thread":"build-19"},{"duration":151,"stepId":"io.quarkus.deployment.steps.ApplicationIndexBuildStep#build","started":"19:10:04.932","dependents":[193,201,143,148],"id":142,"thread":"build-48"},{"duration":132,"stepId":"io.quarkus.arc.deployment.ArcProcessor#buildCompatibleExtensions","started":"19:10:04.924","dependents":[193,183],"id":136,"thread":"build-39"},{"duration":131,"stepId":"io.quarkus.vertx.core.deployment.VertxCoreProcessor#createVertxThreadFactory","started":"19:10:04.898","dependents":[130,235],"id":124,"thread":"build-9"},{"duration":125,"stepId":"io.quarkus.mutiny.deployment.MutinyProcessor#buildTimeInit","started":"19:10:04.897","dependents":[235],"id":115,"thread":"build-4"},{"duration":124,"stepId":"io.quarkus.deployment.steps.ConfigGenerationBuildStep#generateConfigClass","started":"19:10:04.927","dependents":[],"id":133,"thread":"build-40"},{"duration":120,"stepId":"io.quarkus.vertx.core.deployment.VertxCoreProcessor#createVertxContextHandlers","started":"19:10:04.909","dependents":[130,132,235],"id":123,"thread":"build-20"},{"duration":119,"stepId":"io.quarkus.virtual.threads.VirtualThreadsProcessor#setup","started":"19:10:04.933","dependents":[212,211,193,183,235,213],"id":134,"thread":"build-49"},{"duration":118,"stepId":"io.quarkus.deployment.steps.PreloadClassesBuildStep#preInit","started":"19:10:04.904","dependents":[235],"id":117,"thread":"build-5"},{"duration":115,"stepId":"io.quarkus.deployment.dev.io.NioThreadPoolDevModeProcessor#setupTCCL","started":"19:10:04.906","dependents":[235],"id":114,"thread":"build-15"},{"duration":112,"stepId":"io.quarkus.mutiny.reactive.operators.deployment.MutinyReactiveStreamsOperatorsProcessor#classLoadingHack","started":"19:10:04.910","dependents":[235],"id":113,"thread":"build-7"},{"duration":108,"stepId":"io.quarkus.vertx.core.deployment.VertxCoreProcessor#ioThreadDetector","started":"19:10:04.921","dependents":[235,127],"id":126,"thread":"build-17"},{"duration":107,"stepId":"io.quarkus.arc.deployment.ArcProcessor#generateResources","started":"19:10:05.334","dependents":[234,227,233],"id":226,"thread":"build-21"},{"duration":104,"stepId":"io.quarkus.vertx.deployment.VertxProcessor#currentContextFactory","started":"19:10:04.925","dependents":[227,235],"id":122,"thread":"build-34"},{"duration":104,"stepId":"io.quarkus.netty.deployment.NettyProcessor#eagerlyInitClass","started":"19:10:04.918","dependents":[235],"id":112,"thread":"build-32"},{"duration":98,"stepId":"io.quarkus.deployment.steps.RuntimeConfigSetupBuildStep#setupRuntimeConfig","started":"19:10:04.904","dependents":[130,111,151,179,125,180,214,140,235,138,231,129],"id":109,"thread":"build-13"},{"duration":95,"stepId":"io.quarkus.smallrye.reactivemessaging.rabbitmq.deployment.SmallRyeReactiveMessagingRabbitMQProcessor#dynamicCredentials","started":"19:10:04.929","dependents":[212,211,193,183,235,213,225],"id":119,"thread":"build-42"},{"duration":94,"stepId":"io.quarkus.deployment.logging.LoggingResourceProcessor#setupLoggingStaticInit","started":"19:10:04.927","dependents":[235],"id":116,"thread":"build-44"},{"duration":93,"stepId":"io.quarkus.deployment.steps.NativeImageConfigBuildStep#build","started":"19:10:04.936","dependents":[235],"id":121,"thread":"build-51"},{"duration":92,"stepId":"io.quarkus.deployment.logging.LoggingResourceProcessor#registerMetrics","started":"19:10:04.932","dependents":[179,235],"id":120,"thread":"build-28"},{"duration":91,"stepId":"io.quarkus.deployment.console.ConsoleProcessor#helpCommand","started":"19:10:04.905","dependents":[192],"id":108,"thread":"build-12"},{"duration":83,"stepId":"io.quarkus.deployment.ide.IdeProcessor#detectRunningIdeProcesses","started":"19:10:04.906","dependents":[106],"id":105,"thread":"build-6"},{"duration":82,"stepId":"io.quarkus.smallrye.context.deployment.SmallRyeContextPropagationProcessor#buildStatic","started":"19:10:04.950","dependents":[235],"id":128,"thread":"build-47"},{"duration":81,"stepId":"io.quarkus.deployment.steps.ConfigGenerationBuildStep#buildTimeRunTimeConfig","started":"19:10:04.923","dependents":[233,225],"id":110,"thread":"build-31"},{"duration":79,"stepId":"io.quarkus.deployment.console.ConsoleProcessor#quitCommand","started":"19:10:04.918","dependents":[192],"id":107,"thread":"build-29"},{"duration":69,"stepId":"io.quarkus.arc.deployment.ArcProcessor#registerBeans","started":"19:10:05.211","dependents":[203,196,211,215,201,202,195,207,212,200,204,197,213,198,199,205],"id":194,"thread":"build-9"},{"duration":68,"stepId":"io.quarkus.vertx.deployment.VertxProcessor#unremovableBeans","started":"19:10:04.908","dependents":[218,223],"id":100,"thread":"build-23"},{"duration":68,"stepId":"io.quarkus.deployment.steps.ClassPathSystemPropBuildStep#set","started":"19:10:04.955","dependents":[235],"id":118,"thread":"build-21"},{"duration":68,"stepId":"io.quarkus.arc.deployment.ArcProcessor#quarkusMain","started":"19:10:04.909","dependents":[193,183,104],"id":101,"thread":"build-24"},{"duration":65,"stepId":"io.quarkus.deployment.steps.BannerProcessor#recordBanner","started":"19:10:05.003","dependents":[179,235],"id":138,"thread":"build-23"},{"duration":58,"stepId":"io.quarkus.vertx.deployment.VertxProcessor#autoAddScope","started":"19:10:04.919","dependents":[190],"id":102,"thread":"build-25"},{"duration":58,"stepId":"io.quarkus.deployment.index.ApplicationArchiveBuildStep#build","started":"19:10:05.084","dependents":[151,152,234,183,172,149,150,221],"id":148,"thread":"build-17"},{"duration":56,"stepId":"io.quarkus.arc.deployment.ShutdownBuildSteps#addScope","started":"19:10:04.904","dependents":[190],"id":94,"thread":"build-18"},{"duration":54,"stepId":"io.quarkus.arc.deployment.ConfigStaticInitBuildSteps#transformConfigProducer","started":"19:10:04.916","dependents":[193],"id":98,"thread":"build-16"},{"duration":52,"stepId":"io.quarkus.smallrye.reactivemessaging.deployment.SmallRyeReactiveMessagingProcessor#removalExclusions","started":"19:10:04.899","dependents":[218,223],"id":87,"thread":"build-10"},{"duration":52,"stepId":"io.quarkus.arc.deployment.StartupBuildSteps#addScope","started":"19:10:04.904","dependents":[190],"id":92,"thread":"build-11"},{"duration":50,"stepId":"io.quarkus.deployment.steps.ConfigGenerationBuildStep#setupConfigOverride","started":"19:10:04.904","dependents":[],"id":88,"thread":"build-8"},{"duration":43,"stepId":"io.quarkus.netty.deployment.NettyProcessor#setNettyMachineId","started":"19:10:04.929","dependents":[235],"id":99,"thread":"build-46"},{"duration":43,"stepId":"io.quarkus.arc.deployment.LoggingBeanSupportProcessor#discoveredComponents","started":"19:10:04.907","dependents":[193,183,104],"id":84,"thread":"build-22"},{"duration":39,"stepId":"io.quarkus.deployment.dev.HotDeploymentWatchedFileBuildStep#setupWatchedFileHotDeployment","started":"19:10:04.939","dependents":[231],"id":103,"thread":"build-26"},{"duration":38,"stepId":"io.quarkus.deployment.logging.LoggingResourceProcessor#setupLoggingRuntimeInit","started":"19:10:05.149","dependents":[233,180,181,235],"id":179,"thread":"build-9"},{"duration":36,"stepId":"io.quarkus.vertx.core.deployment.VertxCoreProcessor#build_68c59e5d5fe4deeaa2b750dd2b2f234cee36c063","started":"19:10:05.040","dependents":[212,141,206,211,235,213,231],"id":140,"thread":"build-17"},{"duration":36,"stepId":"io.quarkus.smallrye.reactivemessaging.deployment.SmallRyeReactiveMessagingProcessor#beans","started":"19:10:04.915","dependents":[193,183],"id":85,"thread":"build-30"},{"duration":33,"stepId":"io.quarkus.arc.deployment.CommandLineArgumentsProcessor#commandLineArgs","started":"19:10:04.921","dependents":[212,211,193,183,213],"id":89,"thread":"build-21"},{"duration":32,"stepId":"io.quarkus.smallrye.reactivemessaging.deployment.SmallRyeReactiveMessagingProcessor#enableMetrics","started":"19:10:04.932","dependents":[193],"id":97,"thread":"build-27"},{"duration":32,"stepId":"io.quarkus.deployment.steps.ConfigGenerationBuildStep#checkForBuildTimeConfigChange","started":"19:10:05.003","dependents":[235],"id":129,"thread":"build-6"},{"duration":31,"stepId":"io.quarkus.deployment.steps.MainClassBuildStep#build","started":"19:10:05.453","dependents":[],"id":235,"thread":"build-8"},{"duration":30,"stepId":"io.quarkus.arc.deployment.ConfigStaticInitBuildSteps#registerBeans","started":"19:10:04.921","dependents":[193,183],"id":86,"thread":"build-2"},{"duration":30,"stepId":"io.quarkus.arc.deployment.ArcProcessor#validate","started":"19:10:05.303","dependents":[222,234,223,220,221,219,226],"id":218,"thread":"build-29"},{"duration":29,"stepId":"io.quarkus.deployment.steps.ClassPathSystemPropBuildStep#produce","started":"19:10:04.926","dependents":[118],"id":90,"thread":"build-41"},{"duration":27,"stepId":"io.quarkus.arc.deployment.ConfigBuildStep#additionalBeans","started":"19:10:04.923","dependents":[193,183],"id":83,"thread":"build-37"},{"duration":27,"stepId":"io.quarkus.deployment.steps.CapabilityAggregationStep#provideCapabilities","started":"19:10:04.928","dependents":[96],"id":91,"thread":"build-45"},{"duration":26,"stepId":"io.quarkus.vertx.core.deployment.VertxCoreProcessor#eventLoopCount","started":"19:10:05.003","dependents":[235],"id":125,"thread":"build-29"},{"duration":25,"stepId":"io.quarkus.deployment.pkg.steps.JarResultBuildStep#outputTarget","started":"19:10:04.925","dependents":[95],"id":81,"thread":"build-14"},{"duration":25,"stepId":"io.quarkus.arc.deployment.BeanArchiveProcessor#build","started":"19:10:05.170","dependents":[189,184,193,200,204,185,190,188,186],"id":183,"thread":"build-19"},{"duration":24,"stepId":"io.quarkus.arc.deployment.ConfigBuildStep#registerConfigRootsAsBeans","started":"19:10:04.932","dependents":[212,211,213],"id":93,"thread":"build-38"},{"duration":21,"stepId":"io.quarkus.arc.deployment.ArcProcessor#setupExecutor","started":"19:10:05.040","dependents":[235],"id":137,"thread":"build-47"},{"duration":20,"stepId":"io.quarkus.jackson.deployment.JacksonProcessor#generateCustomizer","started":"19:10:05.149","dependents":[183],"id":177,"thread":"build-40"},{"duration":20,"stepId":"io.quarkus.jackson.deployment.JacksonProcessor#unremovable","started":"19:10:05.149","dependents":[218,193,183,223],"id":176,"thread":"build-19"},{"duration":20,"stepId":"io.quarkus.deployment.dev.testing.TestTracingProcessor#testConsoleCommand","started":"19:10:05.149","dependents":[192],"id":178,"thread":"build-39"},{"duration":18,"stepId":"io.quarkus.deployment.steps.ConfigGenerationBuildStep#releaseConfigOnShutdown","started":"19:10:05.003","dependents":[235],"id":111,"thread":"build-12"},{"duration":17,"stepId":"io.quarkus.vertx.core.deployment.VertxCoreProcessor#build_9d6b7122fb368970c50c3a870d1f672392cd8afb","started":"19:10:04.911","dependents":[233,121],"id":64,"thread":"build-27"},{"duration":17,"stepId":"io.quarkus.arc.deployment.ArcProcessor#registerContextPropagation","started":"19:10:04.932","dependents":[128],"id":82,"thread":"build-35"},{"duration":16,"stepId":"io.quarkus.deployment.DockerStatusProcessor#IsDockerWorking","started":"19:10:04.902","dependents":[181,191],"id":41,"thread":"build-14"},{"duration":15,"stepId":"io.quarkus.smallrye.context.deployment.SmallRyeContextPropagationProcessor#build","started":"19:10:05.040","dependents":[212,211,235,213],"id":135,"thread":"build-29"},{"duration":14,"stepId":"io.quarkus.deployment.steps.ConfigGenerationBuildStep#generateMappings","started":"19:10:05.149","dependents":[222,196,223,233,197],"id":174,"thread":"build-6"},{"duration":13,"stepId":"io.quarkus.deployment.CollectionClassProcessor#setupCollectionClasses","started":"19:10:04.897","dependents":[233],"id":21,"thread":"build-2"},{"duration":13,"stepId":"io.quarkus.deployment.steps.ClassTransformingBuildStep#handleClassTransformation","started":"19:10:05.442","dependents":[],"id":234,"thread":"build-24"},{"duration":11,"stepId":"io.quarkus.deployment.steps.RegisterForReflectionBuildStep#build","started":"19:10:05.149","dependents":[233,175],"id":173,"thread":"build-47"},{"duration":11,"stepId":"io.quarkus.deployment.steps.MainClassBuildStep#mainClassBuildStep","started":"19:10:05.149","dependents":[234],"id":172,"thread":"build-21"},{"duration":11,"stepId":"io.quarkus.arc.deployment.ArcProcessor#initialize","started":"19:10:05.200","dependents":[194,204],"id":193,"thread":"build-39"},{"duration":10,"stepId":"io.quarkus.netty.deployment.NettyProcessor#registerQualifiers","started":"19:10:04.927","dependents":[193,183],"id":78,"thread":"build-26"},{"duration":10,"stepId":"io.quarkus.deployment.steps.ThreadPoolSetup#createExecutor","started":"19:10:05.030","dependents":[132,137,135,140,235,131],"id":130,"thread":"build-20"},{"duration":10,"stepId":"io.quarkus.deployment.pkg.steps.FileSystemResourcesBuildStep#notNormalMode","started":"19:10:04.950","dependents":[],"id":95,"thread":"build-50"},{"duration":9,"stepId":"io.quarkus.smallrye.reactivemessaging.deployment.WiringProcessor#extractComponents","started":"19:10:05.280","dependents":[210,208,209,226],"id":207,"thread":"build-19"},{"duration":8,"stepId":"io.quarkus.netty.deployment.NettyProcessor#build","started":"19:10:04.923","dependents":[233,121],"id":74,"thread":"build-35"},{"duration":8,"stepId":"io.quarkus.smallrye.reactivemessaging.deployment.SmallRyeReactiveMessagingProcessor#devmodeSupport","started":"19:10:05.149","dependents":[193,183],"id":171,"thread":"build-36"},{"duration":8,"stepId":"io.quarkus.deployment.steps.ConfigGenerationBuildStep#watchConfigFiles","started":"19:10:04.918","dependents":[103],"id":61,"thread":"build-28"},{"duration":8,"stepId":"io.quarkus.deployment.ide.IdeProcessor#detectIdeFiles","started":"19:10:04.919","dependents":[106],"id":63,"thread":"build-33"},{"duration":8,"stepId":"io.quarkus.deployment.steps.DevModeBuildStep#watchChanges","started":"19:10:04.931","dependents":[103],"id":79,"thread":"build-47"},{"duration":7,"stepId":"io.quarkus.vertx.deployment.VertxProcessor#registerVerticleClasses","started":"19:10:05.149","dependents":[233],"id":168,"thread":"build-44"},{"duration":7,"stepId":"io.quarkus.jackson.deployment.JacksonProcessor#supportMixins","started":"19:10:05.149","dependents":[212,211,233,235,213],"id":170,"thread":"build-5"},{"duration":7,"stepId":"io.quarkus.deployment.logging.LoggingResourceProcessor#setMinLevelForInitialConfigurator","started":"19:10:04.929","dependents":[235],"id":77,"thread":"build-33"},{"duration":7,"stepId":"io.quarkus.deployment.ExtensionLoader#config","started":"19:10:04.913","dependents":[111,234,144,223,125,181,180,201,138,210,52,183,56,235,104,110,148,179,151,189,74,209,60,214,106,122,129,81,116,133,69,193,119,225,231,68,77,227,140,174,71,79,222,70,134,76,82,120,130,159,147,97,166,172,187,142,93,149,80,226],"id":51,"thread":"build-3"},{"duration":7,"stepId":"io.quarkus.deployment.steps.ReflectiveHierarchyStep#build","started":"19:10:05.160","dependents":[233],"id":175,"thread":"build-21"},{"duration":7,"stepId":"io.quarkus.devservices.deployment.DevServicesProcessor#config","started":"19:10:05.192","dependents":[192],"id":191,"thread":"build-40"},{"duration":7,"stepId":"io.quarkus.netty.deployment.NettyProcessor#cleanupUnsafeLog","started":"19:10:04.905","dependents":[179,72],"id":25,"thread":"build-17"},{"duration":7,"stepId":"io.quarkus.smallrye.reactivemessaging.deployment.WiringProcessor#discoverConnectors","started":"19:10:05.281","dependents":[209],"id":205,"thread":"build-29"},{"duration":7,"stepId":"io.quarkus.vertx.core.deployment.VertxCoreProcessor#registerVerticleClasses","started":"19:10:05.149","dependents":[233],"id":167,"thread":"build-29"},{"duration":7,"stepId":"io.quarkus.smallrye.reactivemessaging.deployment.SmallRyeReactiveMessagingProcessor#duplicatedContextSupport","started":"19:10:05.149","dependents":[193,183],"id":169,"thread":"build-42"},{"duration":6,"stepId":"io.quarkus.arc.deployment.ReflectiveBeanClassesProcessor#implicitReflectiveBeanClasses","started":"19:10:05.280","dependents":[226],"id":202,"thread":"build-21"},{"duration":6,"stepId":"io.quarkus.vertx.deployment.VertxProcessor#collectEventConsumers","started":"19:10:05.280","dependents":[206,215],"id":203,"thread":"build-39"},{"duration":6,"stepId":"io.quarkus.deployment.steps.ConfigGenerationBuildStep#generateBuilders","started":"19:10:05.335","dependents":[233],"id":225,"thread":"build-39"},{"duration":6,"stepId":"io.quarkus.deployment.steps.CombinedIndexBuildStep#build","started":"19:10:05.142","dependents":[153,171,193,158,157,173,161,163,178,167,197,155,154,174,188,205,177,179,176,160,196,159,156,165,166,169,172,162,175,170,168],"id":152,"thread":"build-48"},{"duration":6,"stepId":"io.quarkus.deployment.logging.LoggingResourceProcessor#setupStackTraceFormatter","started":"19:10:05.142","dependents":[179],"id":150,"thread":"build-36"},{"duration":6,"stepId":"io.quarkus.arc.deployment.SyntheticBeansProcessor#initRegular","started":"19:10:05.292","dependents":[215],"id":213,"thread":"build-44"},{"duration":6,"stepId":"io.quarkus.deployment.steps.ConfigGenerationBuildStep#unknownConfigFiles","started":"19:10:05.142","dependents":[235],"id":151,"thread":"build-19"},{"duration":6,"stepId":"io.quarkus.deployment.recording.substitutions.AdditionalSubstitutionsBuildStep#additionalSubstitutions","started":"19:10:04.910","dependents":[235],"id":34,"thread":"build-25"},{"duration":6,"stepId":"io.quarkus.jackson.deployment.JacksonProcessor#jacksonSupport","started":"19:10:05.149","dependents":[212,211,235,213],"id":166,"thread":"build-28"},{"duration":5,"stepId":"io.quarkus.deployment.steps.ReflectiveHierarchyStep#ignoreJavaClassWarnings","started":"19:10:04.919","dependents":[175],"id":58,"thread":"build-14"},{"duration":5,"stepId":"io.quarkus.arc.deployment.UnremovableAnnotationsProcessor#unremovableBeans","started":"19:10:04.919","dependents":[218,223],"id":59,"thread":"build-34"},{"duration":5,"stepId":"io.quarkus.deployment.dev.testing.TestTracingProcessor#handle","started":"19:10:04.907","dependents":[179,72],"id":24,"thread":"build-3"},{"duration":5,"stepId":"io.quarkus.deployment.dev.testing.TestTracingProcessor#sharedStateListener","started":"19:10:04.905","dependents":[147],"id":23,"thread":"build-16"},{"duration":5,"stepId":"io.quarkus.mutiny.deployment.MutinyProcessor#runtimeInit","started":"19:10:05.040","dependents":[235],"id":132,"thread":"build-6"},{"duration":5,"stepId":"io.quarkus.deployment.steps.CapabilityAggregationStep#aggregateCapabilities","started":"19:10:04.956","dependents":[176,193,175,145,173],"id":96,"thread":"build-41"},{"duration":5,"stepId":"io.quarkus.deployment.pkg.steps.PackageTypeVerificationBuildStep#verify","started":"19:10:04.934","dependents":[231],"id":80,"thread":"build-50"},{"duration":5,"stepId":"io.quarkus.arc.deployment.ConfigBuildStep#validateConfigValues","started":"19:10:05.447","dependents":[233,235],"id":232,"thread":"build-21"},{"duration":5,"stepId":"io.quarkus.arc.deployment.ConfigBuildStep#generateConfigProperties","started":"19:10:05.149","dependents":[222,196,223,233,197],"id":165,"thread":"build-51"},{"duration":5,"stepId":"io.quarkus.arc.deployment.SyntheticBeansProcessor#initRuntime","started":"19:10:05.292","dependents":[214,215,235,231],"id":212,"thread":"build-19"},{"duration":5,"stepId":"io.quarkus.deployment.logging.LoggingResourceProcessor#setUpDefaultLevels","started":"19:10:04.909","dependents":[179,225],"id":30,"thread":"build-21"},{"duration":4,"stepId":"io.quarkus.arc.deployment.BuildTimeEnabledProcessor#unlessBuildProperty","started":"19:10:05.150","dependents":[164],"id":162,"thread":"build-4"},{"duration":4,"stepId":"io.quarkus.jackson.deployment.JacksonProcessor#register","started":"19:10:05.149","dependents":[193,183,233,175],"id":158,"thread":"build-23"},{"duration":4,"stepId":"io.quarkus.deployment.execannotations.ExecutionModelAnnotationsProcessor#devuiJsonRpcServices","started":"19:10:04.927","dependents":[159],"id":73,"thread":"build-28"},{"duration":4,"stepId":"io.quarkus.arc.deployment.ConfigBuildStep#vetoMPConfigProperties","started":"19:10:04.913","dependents":[193],"id":37,"thread":"build-28"},{"duration":4,"stepId":"io.quarkus.arc.deployment.TestsAsBeansProcessor#testAnnotations","started":"19:10:04.901","dependents":[193,183,104],"id":11,"thread":"build-12"},{"duration":4,"stepId":"io.quarkus.arc.deployment.HotDeploymentConfigBuildStep#startup","started":"19:10:04.919","dependents":[67],"id":57,"thread":"build-26"},{"duration":4,"stepId":"io.quarkus.deployment.steps.AdditionalClassLoaderResourcesBuildStep#appendAdditionalClassloaderResources","started":"19:10:04.913","dependents":[152],"id":36,"thread":"build-17"},{"duration":4,"stepId":"io.quarkus.deployment.execannotations.ExecutionModelAnnotationsProcessor#check","started":"19:10:05.149","dependents":[],"id":159,"thread":"build-20"},{"duration":4,"stepId":"io.quarkus.smallrye.context.deployment.SmallRyeContextPropagationProcessor#transformInjectionPoint","started":"19:10:04.904","dependents":[193],"id":16,"thread":"build-7"},{"duration":4,"stepId":"io.quarkus.arc.deployment.WrongAnnotationUsageProcessor#detect","started":"19:10:05.280","dependents":[226],"id":201,"thread":"build-6"},{"duration":4,"stepId":"io.quarkus.vertx.core.deployment.VertxCoreProcessor#doNotRemoveVertxOptionsCustomizers","started":"19:10:04.917","dependents":[218,223],"id":48,"thread":"build-2"},{"duration":4,"stepId":"io.quarkus.arc.deployment.SplitPackageProcessor#splitPackageDetection","started":"19:10:05.142","dependents":[226],"id":149,"thread":"build-23"},{"duration":4,"stepId":"io.quarkus.arc.deployment.BuildTimeEnabledProcessor#ifBuildProperty","started":"19:10:05.150","dependents":[164],"id":163,"thread":"build-49"},{"duration":4,"stepId":"io.quarkus.arc.deployment.LifecycleEventsBuildStep#startupEvent","started":"19:10:05.447","dependents":[235],"id":231,"thread":"build-2"},{"duration":4,"stepId":"io.quarkus.arc.deployment.StartupBuildSteps#unremovableBeans","started":"19:10:04.927","dependents":[218,223],"id":75,"thread":"build-43"},{"duration":3,"stepId":"io.quarkus.smallrye.reactivemessaging.deployment.devui.ReactiveMessagingDevUIProcessor#beans","started":"19:10:04.898","dependents":[193,183],"id":2,"thread":"build-7"},{"duration":3,"stepId":"io.quarkus.deployment.dev.IsolatedDevModeMain$5$1@1ebf5f1c","started":"19:10:04.911","dependents":[193],"id":29,"thread":"build-26"},{"duration":3,"stepId":"io.quarkus.arc.deployment.SyntheticBeansProcessor#initStatic","started":"19:10:05.292","dependents":[215,235],"id":211,"thread":"build-29"},{"duration":3,"stepId":"io.quarkus.deployment.ide.IdeProcessor#effectiveIde","started":"19:10:04.989","dependents":[146,150],"id":106,"thread":"build-23"},{"duration":3,"stepId":"io.quarkus.arc.deployment.staticmethods.InterceptedStaticMethodsProcessor#callInitializer","started":"19:10:05.448","dependents":[235],"id":230,"thread":"build-8"},{"duration":3,"stepId":"io.quarkus.smallrye.context.deployment.SmallRyeContextPropagationProcessor#createSynthBeansForConfiguredInjectionPoints","started":"19:10:05.280","dependents":[212,211,235,213],"id":199,"thread":"build-44"},{"duration":3,"stepId":"io.quarkus.deployment.logging.LoggingResourceProcessor#setUpDarkeningDefault","started":"19:10:04.897","dependents":[225],"id":4,"thread":"build-3"},{"duration":3,"stepId":"io.quarkus.vertx.deployment.EventBusCodecProcessor#registerCodecs","started":"19:10:05.195","dependents":[206,233],"id":188,"thread":"build-6"},{"duration":3,"stepId":"io.quarkus.arc.deployment.BuildTimeEnabledProcessor#ifBuildProfile","started":"19:10:05.150","dependents":[164],"id":161,"thread":"build-15"},{"duration":3,"stepId":"io.quarkus.deployment.dev.ConfigureDisableInstrumentationBuildStep#configure","started":"19:10:04.926","dependents":[231],"id":67,"thread":"build-42"},{"duration":3,"stepId":"io.quarkus.vertx.deployment.EventConsumerMethodsProcessor#eventConsumerMethods","started":"19:10:04.905","dependents":[159],"id":17,"thread":"build-20"},{"duration":3,"stepId":"io.quarkus.smallrye.reactivemessaging.deployment.ReactiveMessagingMethodsProcessor#reactiveMessagingMethods","started":"19:10:04.912","dependents":[159],"id":33,"thread":"build-2"},{"duration":3,"stepId":"io.quarkus.arc.deployment.ArcProcessor#launchMode","started":"19:10:04.898","dependents":[193,183],"id":5,"thread":"build-8"},{"duration":3,"stepId":"io.quarkus.smallrye.reactivemessaging.deployment.SmallRyeReactiveMessagingProcessor#build","started":"19:10:05.289","dependents":[212,211,233,235,213,225],"id":210,"thread":"build-21"},{"duration":3,"stepId":"io.quarkus.arc.deployment.BuildTimeEnabledProcessor#unlessBuildProfile","started":"19:10:05.150","dependents":[164],"id":160,"thread":"build-48"},{"duration":3,"stepId":"io.quarkus.arc.deployment.AutoProducerMethodsProcessor#annotationTransformer","started":"19:10:05.195","dependents":[193],"id":189,"thread":"build-39"},{"duration":3,"stepId":"io.quarkus.arc.deployment.ArcProcessor#unremovableAsyncObserverExceptionHandlers","started":"19:10:04.900","dependents":[218,223],"id":8,"thread":"build-11"},{"duration":3,"stepId":"io.quarkus.netty.deployment.NettyProcessor#cleanupMacDNSInLog","started":"19:10:04.914","dependents":[179,72],"id":38,"thread":"build-29"},{"duration":3,"stepId":"io.quarkus.deployment.ConstructorPropertiesProcessor#build","started":"19:10:05.149","dependents":[233],"id":157,"thread":"build-17"},{"duration":3,"stepId":"io.quarkus.vertx.core.deployment.VertxCoreProcessor#overrideContextInternalInterfaceToAddSafeGuards","started":"19:10:04.912","dependents":[234],"id":31,"thread":"build-16"},{"duration":3,"stepId":"io.quarkus.vertx.deployment.VertxProcessor#registerBean","started":"19:10:04.914","dependents":[193,183],"id":42,"thread":"build-26"},{"duration":3,"stepId":"io.quarkus.netty.deployment.NettyProcessor#registerEventLoopBeans","started":"19:10:05.077","dependents":[212,211,235,213],"id":141,"thread":"build-19"},{"duration":3,"stepId":"io.quarkus.arc.deployment.staticmethods.InterceptedStaticMethodsProcessor#collectInterceptedStaticMethods","started":"19:10:05.280","dependents":[218,204,223,230],"id":200,"thread":"build-36"},{"duration":3,"stepId":"io.quarkus.deployment.pkg.steps.PackageTypeVerificationBuildStep#builtins","started":"19:10:04.897","dependents":[80],"id":3,"thread":"build-5"},{"duration":2,"stepId":"io.quarkus.smallrye.reactivemessaging.deployment.devui.ReactiveMessagingDevUIProcessor#collectInjectionInfo","started":"19:10:05.280","dependents":[235],"id":198,"thread":"build-42"},{"duration":2,"stepId":"io.quarkus.arc.deployment.ArcProcessor#loggerProducer","started":"19:10:04.916","dependents":[193,183],"id":43,"thread":"build-31"},{"duration":2,"stepId":"io.quarkus.smallrye.reactivemessaging.rabbitmq.deployment.devui.RabbitDevUIProcessor#beans","started":"19:10:04.918","dependents":[193,183],"id":45,"thread":"build-17"},{"duration":2,"stepId":"io.quarkus.deployment.steps.ProfileBuildStep#defaultProfile","started":"19:10:04.904","dependents":[225],"id":15,"thread":"build-3"},{"duration":2,"stepId":"io.quarkus.smallrye.reactivemessaging.deployment.SmallRyeReactiveMessagingProcessor#producesCoroutineConfiguration","started":"19:10:04.897","dependents":[10],"id":1,"thread":"build-6"},{"duration":2,"stepId":"io.quarkus.arc.deployment.AutoInjectFieldProcessor#autoInjectQualifiers","started":"19:10:05.195","dependents":[187,190],"id":186,"thread":"build-47"},{"duration":2,"stepId":"io.quarkus.arc.deployment.ArcProcessor#registerSyntheticObservers","started":"19:10:05.299","dependents":[218,216,223,233,226,217],"id":215,"thread":"build-19"},{"duration":2,"stepId":"io.quarkus.vertx.core.deployment.VertxCoreProcessor#registerSafeDuplicatedContextInterceptor","started":"19:10:04.919","dependents":[193,183],"id":53,"thread":"build-31"},{"duration":2,"stepId":"io.quarkus.arc.deployment.ConfigBuildStep#registerConfigMappingsBean","started":"19:10:05.281","dependents":[215],"id":197,"thread":"build-5"},{"duration":2,"stepId":"io.quarkus.deployment.steps.DevServicesConfigBuildStep#setup","started":"19:10:05.190","dependents":[225,231,191],"id":182,"thread":"build-39"},{"duration":2,"stepId":"io.quarkus.arc.deployment.ArcProcessor#initializeContainer","started":"19:10:05.442","dependents":[235,228],"id":227,"thread":"build-16"},{"duration":2,"stepId":"io.quarkus.deployment.logging.LoggingResourceProcessor#setUpDefaultLogCleanupFilters","started":"19:10:04.929","dependents":[225],"id":72,"thread":"build-27"},{"duration":2,"stepId":"io.quarkus.smallrye.reactivemessaging.rabbitmq.deployment.RabbitMQDevServicesProcessor#startRabbitMQDevService","started":"19:10:05.187","dependents":[182,191],"id":181,"thread":"build-40"},{"duration":2,"stepId":"io.quarkus.deployment.dev.testing.TestTracingProcessor#startTesting","started":"19:10:05.088","dependents":[179,231],"id":147,"thread":"build-19"},{"duration":2,"stepId":"io.quarkus.arc.deployment.ConfigBuildStep#registerConfigPropertiesBean","started":"19:10:05.280","dependents":[215],"id":196,"thread":"build-40"},{"duration":2,"stepId":"io.quarkus.arc.deployment.ShutdownBuildSteps#unremovableBeans","started":"19:10:04.906","dependents":[218,223],"id":18,"thread":"build-21"},{"duration":2,"stepId":"io.quarkus.deployment.steps.ConfigGenerationBuildStep#runtimeOverrideConfig","started":"19:10:04.907","dependents":[225],"id":20,"thread":"build-19"},{"duration":2,"stepId":"io.quarkus.config.yaml.deployment.ConfigYamlProcessor#yamlConfig","started":"19:10:04.917","dependents":[225],"id":44,"thread":"build-21"},{"duration":2,"stepId":"io.quarkus.arc.deployment.staticmethods.InterceptedStaticMethodsProcessor#processInterceptedStaticMethods","started":"19:10:05.284","dependents":[234,233],"id":204,"thread":"build-44"},{"duration":2,"stepId":"io.quarkus.vertx.deployment.VertxProcessor#build","started":"19:10:05.287","dependents":[233,235,231],"id":206,"thread":"build-21"},{"duration":2,"stepId":"io.quarkus.arc.deployment.ArcProcessor#signalBeanContainerReady","started":"19:10:05.445","dependents":[232,235,230,231],"id":229,"thread":"build-14"},{"duration":2,"stepId":"io.quarkus.deployment.steps.BlockingOperationControlBuildStep#blockingOP","started":"19:10:05.030","dependents":[235],"id":127,"thread":"build-29"},{"duration":2,"stepId":"io.quarkus.arc.deployment.devui.ArcDevUIProcessor#registerMonitoringComponents","started":"19:10:04.978","dependents":[193,183],"id":104,"thread":"build-23"},{"duration":2,"stepId":"io.quarkus.config.yaml.deployment.ConfigYamlProcessor#feature","started":"19:10:04.902","dependents":[235],"id":12,"thread":"build-15"},{"duration":1,"stepId":"io.quarkus.arc.deployment.BuildTimeEnabledProcessor#findEnablementStereotypes","started":"19:10:05.149","dependents":[163,160,162,161],"id":156,"thread":"build-34"},{"duration":1,"stepId":"io.quarkus.deployment.console.ConsoleProcessor#setupExceptionHandler","started":"19:10:05.088","dependents":[150],"id":146,"thread":"build-48"},{"duration":1,"stepId":"io.quarkus.arc.deployment.ConfigBuildStep#validateConfigMappingsInjectionPoints","started":"19:10:05.334","dependents":[224,225],"id":223,"thread":"build-19"},{"duration":1,"stepId":"io.quarkus.smallrye.context.deployment.SmallRyeContextPropagationProcessor#registerBean","started":"19:10:04.904","dependents":[193,183],"id":13,"thread":"build-6"},{"duration":1,"stepId":"io.quarkus.arc.deployment.ConfigBuildStep#registerConfigClasses","started":"19:10:05.335","dependents":[235],"id":224,"thread":"build-44"},{"duration":1,"stepId":"io.quarkus.arc.deployment.init.InitializationTaskProcessor#startApplicationInitializer","started":"19:10:05.298","dependents":[235],"id":214,"thread":"build-29"},{"duration":1,"stepId":"io.quarkus.arc.deployment.ArcProcessor#exposeCustomScopeNames","started":"19:10:04.901","dependents":[189,94,193,183,201,185,190,104,92],"id":6,"thread":"build-13"},{"duration":1,"stepId":"io.quarkus.deployment.steps.ShutdownListenerBuildStep#setupShutdown","started":"19:10:05.187","dependents":[235],"id":180,"thread":"build-39"},{"duration":1,"stepId":"io.quarkus.deployment.console.ConsoleProcessor#missingDevUIMessageHandler","started":"19:10:05.088","dependents":[231],"id":145,"thread":"build-23"},{"duration":1,"stepId":"io.quarkus.smallrye.reactivemessaging.deployment.WiringProcessor#autoConfigureConnectorForOrphansAndProduceManagedChannels","started":"19:10:05.290","dependents":[225,226],"id":209,"thread":"build-19"},{"duration":1,"stepId":"io.quarkus.smallrye.reactivemessaging.deployment.SmallRyeReactiveMessagingProcessor#transformBeanScope","started":"19:10:05.195","dependents":[193],"id":185,"thread":"build-21"},{"duration":1,"stepId":"io.quarkus.smallrye.reactivemessaging.deployment.SmallRyeReactiveMessagingProcessor#produceCoroutineScope","started":"19:10:04.903","dependents":[193,183],"id":10,"thread":"build-16"},{"duration":1,"stepId":"io.quarkus.arc.deployment.HotDeploymentConfigBuildStep#configFile","started":"19:10:04.917","dependents":[103],"id":39,"thread":"build-25"},{"duration":1,"stepId":"io.quarkus.deployment.SslProcessor#setupNativeSsl","started":"19:10:04.932","dependents":[121],"id":76,"thread":"build-43"},{"duration":1,"stepId":"io.quarkus.deployment.recording.AnnotationProxyBuildStep#build","started":"19:10:05.084","dependents":[206],"id":143,"thread":"build-19"},{"duration":1,"stepId":"io.quarkus.arc.deployment.LookupConditionsProcessor#suppressConditionsGenerators","started":"19:10:05.195","dependents":[193],"id":184,"thread":"build-9"},{"duration":1,"stepId":"io.quarkus.arc.deployment.AutoAddScopeProcessor#annotationTransformer","started":"19:10:05.198","dependents":[218,193,223],"id":190,"thread":"build-9"},{"duration":1,"stepId":"io.quarkus.arc.deployment.AutoInjectFieldProcessor#annotationTransformer","started":"19:10:05.198","dependents":[193],"id":187,"thread":"build-21"},{"duration":1,"stepId":"io.quarkus.deployment.steps.DevServicesConfigBuildStep#deprecated","started":"19:10:04.904","dependents":[182],"id":14,"thread":"build-19"},{"duration":0,"stepId":"io.quarkus.deployment.steps.ConfigGenerationBuildStep#suppressNonRuntimeConfigChanged","started":"19:10:04.916","dependents":[129],"id":32,"thread":"build-21"},{"duration":0,"stepId":"io.quarkus.deployment.JniProcessor#setupJni","started":"19:10:04.930","dependents":[121],"id":69,"thread":"build-47"},{"duration":0,"stepId":"io.quarkus.deployment.console.ConsoleProcessor#installCliCommands","started":"19:10:05.200","dependents":[231],"id":192,"thread":"build-9"},{"duration":0,"stepId":"io.quarkus.vertx.core.deployment.VertxCoreProcessor#cleanupVertxWarnings","started":"19:10:04.911","dependents":[179,72],"id":27,"thread":"build-2"},{"duration":0,"stepId":"io.quarkus.smallrye.reactivemessaging.rabbitmq.deployment.SmallRyeReactiveMessagingRabbitMQProcessor#feature","started":"19:10:04.918","dependents":[235],"id":40,"thread":"build-33"},{"duration":0,"stepId":"io.quarkus.deployment.steps.CurateOutcomeBuildStep#removeResources","started":"19:10:04.929","dependents":[234],"id":68,"thread":"build-38"},{"duration":0,"stepId":"io.quarkus.deployment.steps.MainClassBuildStep#applicationReflection","started":"19:10:04.929","dependents":[233],"id":65,"thread":"build-27"},{"duration":0,"stepId":"io.quarkus.netty.deployment.NettyProcessor#limitArenaSize","started":"19:10:04.931","dependents":[235],"id":70,"thread":"build-38"},{"duration":0,"stepId":"io.quarkus.arc.deployment.ArcProcessor#validateAsyncObserverExceptionHandlers","started":"19:10:05.334","dependents":[226],"id":220,"thread":"build-21"},{"duration":0,"stepId":"io.quarkus.arc.deployment.ShutdownBuildSteps#registerShutdownObservers","started":"19:10:05.302","dependents":[218],"id":216,"thread":"build-29"},{"duration":0,"stepId":"io.quarkus.deployment.index.ApplicationArchiveBuildStep#addConfiguredIndexedDependencies","started":"19:10:04.931","dependents":[148],"id":71,"thread":"build-48"},{"duration":0,"stepId":"io.quarkus.arc.deployment.TestsAsBeansProcessor#testClassBeans","started":"19:10:04.927","dependents":[193,183],"id":62,"thread":"build-40"},{"duration":0,"stepId":"io.quarkus.arc.deployment.ArcProcessor#quarkusApplication","started":"19:10:05.149","dependents":[193,183],"id":153,"thread":"build-19"},{"duration":0,"stepId":"io.quarkus.deployment.steps.PreloadClassesBuildStep#registerPreInitClasses","started":"19:10:04.921","dependents":[],"id":49,"thread":"build-35"},{"duration":0,"stepId":"io.quarkus.arc.deployment.ArcProcessor#marker","started":"19:10:04.922","dependents":[148],"id":55,"thread":"build-31"},{"duration":0,"stepId":"io.quarkus.deployment.logging.LoggingResourceProcessor#setProperty","started":"19:10:04.912","dependents":[235],"id":28,"thread":"build-3"},{"duration":0,"stepId":"io.quarkus.deployment.steps.BannerProcessor#watchBannerChanges","started":"19:10:04.921","dependents":[103],"id":52,"thread":"build-35"},{"duration":0,"stepId":"io.quarkus.deployment.logging.LoggingWithPanacheProcessor#process","started":"19:10:05.149","dependents":[234],"id":154,"thread":"build-40"},{"duration":0,"stepId":"io.quarkus.arc.deployment.ConfigBuildStep#registerCustomConfigBeanTypes","started":"19:10:05.280","dependents":[212,211,233,213],"id":195,"thread":"build-47"},{"duration":0,"stepId":"io.quarkus.arc.deployment.BuildTimeEnabledProcessor#conditionTransformer","started":"19:10:05.155","dependents":[193],"id":164,"thread":"build-4"},{"duration":0,"stepId":"io.quarkus.deployment.steps.CurateOutcomeBuildStep#curateOutcome","started":"19:10:04.923","dependents":[118,68,234,96,158,142,90,148,91],"id":56,"thread":"build-38"},{"duration":0,"stepId":"io.quarkus.arc.deployment.ConfigBuildStep#validateConfigInjectionPoints","started":"19:10:05.334","dependents":[232],"id":219,"thread":"build-6"},{"duration":0,"stepId":"io.quarkus.vertx.core.deployment.VertxCoreProcessor#preventLoggerContention","started":"19:10:04.909","dependents":[30],"id":19,"thread":"build-7"},{"duration":0,"stepId":"io.quarkus.deployment.ForkJoinPoolProcessor#setProperty","started":"19:10:04.903","dependents":[235],"id":7,"thread":"build-17"},{"duration":0,"stepId":"io.quarkus.arc.deployment.StartupBuildSteps#registerStartupObservers","started":"19:10:05.302","dependents":[218],"id":217,"thread":"build-44"},{"duration":0,"stepId":"io.quarkus.config.yaml.deployment.ConfigYamlProcessor#watchYamlConfig","started":"19:10:04.920","dependents":[103],"id":47,"thread":"build-35"},{"duration":0,"stepId":"io.quarkus.deployment.pkg.steps.NativeImageBuildStep#ignoreBuildPropertyChanges","started":"19:10:04.920","dependents":[129],"id":46,"thread":"build-21"},{"duration":0,"stepId":"io.quarkus.arc.deployment.ObserverValidationProcessor#validateApplicationObserver","started":"19:10:05.334","dependents":[226],"id":221,"thread":"build-39"},{"duration":0,"stepId":"io.quarkus.arc.deployment.ConfigBuildStep#validateConfigPropertiesInjectionPoints","started":"19:10:05.334","dependents":[224],"id":222,"thread":"build-44"},{"duration":0,"stepId":"io.quarkus.vertx.deployment.VertxProcessor#featureAndCapability","started":"19:10:04.921","dependents":[96,235],"id":50,"thread":"build-36"},{"duration":0,"stepId":"io.quarkus.smallrye.reactivemessaging.deployment.SmallRyeReactiveMessagingProcessor#disableObservation","started":"19:10:04.917","dependents":[225],"id":35,"thread":"build-32"},{"duration":0,"stepId":"io.quarkus.deployment.logging.LoggingResourceProcessor#setupLogFilters","started":"19:10:04.929","dependents":[179,72],"id":66,"thread":"build-38"},{"duration":0,"stepId":"io.quarkus.arc.deployment.ArcProcessor#feature","started":"19:10:04.922","dependents":[235],"id":54,"thread":"build-35"},{"duration":0,"stepId":"io.quarkus.jackson.deployment.JacksonProcessor#autoRegisterModules","started":"19:10:05.149","dependents":[177],"id":155,"thread":"build-49"},{"duration":0,"stepId":"io.quarkus.arc.deployment.ExecutorServiceProcessor#executorServiceBean","started":"19:10:05.040","dependents":[212,211,213],"id":131,"thread":"build-9"},{"duration":0,"stepId":"io.quarkus.smallrye.reactivemessaging.deployment.WiringProcessor#detectOrphanChannels","started":"19:10:05.290","dependents":[209],"id":208,"thread":"build-29"},{"duration":0,"stepId":"io.quarkus.vertx.core.deployment.VertxCoreProcessor#filterNettyHostsFileParsingWarn","started":"19:10:04.911","dependents":[179,72],"id":26,"thread":"build-16"},{"duration":0,"stepId":"io.quarkus.arc.deployment.ArcProcessor#notifyBeanContainerListeners","started":"19:10:05.444","dependents":[229,235],"id":228,"thread":"build-21"},{"duration":0,"stepId":"io.quarkus.deployment.steps.ApplicationInfoBuildStep#create","started":"19:10:04.925","dependents":[235],"id":60,"thread":"build-40"},{"duration":0,"stepId":"io.quarkus.deployment.ExtensionLoader#booleanSupplierFactory","started":"19:10:04.904","dependents":[91],"id":9,"thread":"build-17"},{"duration":0,"stepId":"io.quarkus.smallrye.reactivemessaging.deployment.SmallRyeReactiveMessagingProcessor#feature","started":"19:10:04.910","dependents":[235],"id":22,"thread":"build-2"},{"duration":0,"stepId":"io.quarkus.deployment.steps.ReflectionDiagnosticProcessor#writeReflectionData","started":"19:10:05.453","dependents":[],"id":233,"thread":"build-2"}],"started":"2026-05-04T19:10:04.896","items":[{"count":222,"class":"io.quarkus.deployment.builditem.GeneratedClassBuildItem"},{"count":214,"class":"io.quarkus.deployment.builditem.nativeimage.ReflectiveClassBuildItem"},{"count":44,"class":"io.quarkus.deployment.builditem.nativeimage.ReflectiveMethodBuildItem"},{"count":35,"class":"io.quarkus.deployment.builditem.nativeimage.ReflectiveFieldBuildItem"},{"count":28,"class":"io.quarkus.deployment.builditem.nativeimage.RuntimeInitializedClassBuildItem"},{"count":27,"class":"io.quarkus.deployment.builditem.MainBytecodeRecorderBuildItem"},{"count":26,"class":"io.quarkus.arc.deployment.SyntheticBeanBuildItem"},{"count":20,"class":"io.quarkus.arc.deployment.AdditionalBeanBuildItem"},{"count":20,"class":"io.quarkus.deployment.builditem.StaticBytecodeRecorderBuildItem"},{"count":18,"class":"io.quarkus.deployment.builditem.HotDeploymentWatchedFileBuildItem"},{"count":13,"class":"io.quarkus.arc.deployment.UnremovableBeanBuildItem"},{"count":12,"class":"io.quarkus.deployment.builditem.RunTimeConfigurationDefaultBuildItem"},{"count":11,"class":"io.quarkus.deployment.builditem.SuppressNonRuntimeConfigChangedWarningBuildItem"},{"count":10,"class":"io.quarkus.arc.deployment.AnnotationsTransformerBuildItem"},{"count":8,"class":"io.quarkus.deployment.builditem.nativeimage.RuntimeReinitializedClassBuildItem"},{"count":8,"class":"io.quarkus.arc.deployment.ConfigPropertyBuildItem"},{"count":7,"class":"io.quarkus.deployment.pkg.builditem.PackageTypeBuildItem"},{"count":6,"class":"io.quarkus.deployment.logging.LogCleanupFilterBuildItem"},{"count":6,"class":"io.quarkus.deployment.builditem.FeatureBuildItem"},{"count":6,"class":"io.quarkus.deployment.builditem.CapabilityBuildItem"},{"count":6,"class":"io.quarkus.deployment.builditem.nativeimage.NativeImageSystemPropertyBuildItem"},{"count":5,"class":"io.quarkus.deployment.builditem.SystemPropertyBuildItem"},{"count":5,"class":"io.quarkus.deployment.builditem.ConsoleCommandBuildItem"},{"count":5,"class":"io.quarkus.deployment.builditem.ConfigClassBuildItem"},{"count":3,"class":"io.quarkus.deployment.builditem.RunTimeConfigBuilderBuildItem"},{"count":3,"class":"io.quarkus.arc.deployment.AutoAddScopeBuildItem"},{"count":3,"class":"io.quarkus.deployment.execannotations.ExecutionModelAnnotationsAllowedBuildItem"},{"count":3,"class":"io.quarkus.deployment.builditem.StaticInitConfigBuilderBuildItem"},{"count":3,"class":"io.quarkus.jackson.spi.ClassPathJacksonModuleBuildItem"},{"count":3,"class":"io.quarkus.deployment.builditem.AdditionalApplicationArchiveMarkerBuildItem"},{"count":2,"class":"io.quarkus.smallrye.reactivemessaging.deployment.items.ConnectorBuildItem"},{"count":2,"class":"io.quarkus.deployment.builditem.ObjectSubstitutionBuildItem"},{"count":2,"class":"io.quarkus.deployment.builditem.nativeimage.NativeImageConfigBuildItem"},{"count":2,"class":"io.quarkus.arc.deployment.BeanDefiningAnnotationBuildItem"},{"count":2,"class":"io.quarkus.deployment.builditem.BytecodeTransformerBuildItem"},{"count":2,"class":"io.quarkus.deployment.dev.testing.TestListenerBuildItem"},{"count":2,"class":"io.quarkus.deployment.builditem.ServiceStartBuildItem"},{"count":2,"class":"io.quarkus.deployment.builditem.BytecodeRecorderObjectLoaderBuildItem"},{"count":1,"class":"io.quarkus.deployment.builditem.AnnotationProxyBuildItem"},{"count":1,"class":"io.quarkus.deployment.builditem.TransformedClassesBuildItem"},{"count":1,"class":"io.quarkus.netty.deployment.EventLoopGroupBuildItem"},{"count":1,"class":"io.quarkus.deployment.console.ConsoleInstalledBuildItem"},{"count":1,"class":"io.quarkus.arc.deployment.BeanDiscoveryFinishedBuildItem"},{"count":1,"class":"io.quarkus.deployment.builditem.RunTimeConfigurationProxyBuildItem"},{"count":1,"class":"io.quarkus.arc.deployment.SynthesisFinishedBuildItem"},{"count":1,"class":"io.quarkus.deployment.builditem.ShutdownListenerBuildItem"},{"count":1,"class":"io.quarkus.vertx.core.deployment.EventLoopCountBuildItem"},{"count":1,"class":"io.quarkus.vertx.core.deployment.CoreVertxBuildItem"},{"count":1,"class":"io.quarkus.arc.deployment.BuildCompatibleExtensionsBuildItem"},{"count":1,"class":"io.quarkus.deployment.builditem.DockerStatusBuildItem"},{"count":1,"class":"io.quarkus.deployment.builditem.nativeimage.ReflectiveHierarchyIgnoreWarningBuildItem"},{"count":1,"class":"io.quarkus.vertx.deployment.LocalCodecSelectorTypesBuildItem"},{"count":1,"class":"io.quarkus.arc.deployment.InterceptorResolverBuildItem"},{"count":1,"class":"io.quarkus.deployment.dev.ExceptionNotificationBuildItem"},{"count":1,"class":"io.quarkus.arc.deployment.ValidationPhaseBuildItem"},{"count":1,"class":"io.quarkus.smallrye.reactivemessaging.deployment.SmallRyeReactiveMessagingProcessor$CoroutineConfigurationBuildItem"},{"count":1,"class":"io.quarkus.netty.deployment.EventLoopSupplierBuildItem"},{"count":1,"class":"io.quarkus.smallrye.reactivemessaging.deployment.items.ConnectorManagedChannelBuildItem"},{"count":1,"class":"io.quarkus.arc.deployment.BeanArchiveIndexBuildItem"},{"count":1,"class":"io.quarkus.deployment.builditem.ConsoleFormatterBannerBuildItem"},{"count":1,"class":"io.quarkus.arc.deployment.SuppressConditionGeneratorBuildItem"},{"count":1,"class":"io.quarkus.arc.deployment.BuildTimeEnabledStereotypesBuildItem"},{"count":1,"class":"io.quarkus.deployment.builditem.ApplicationArchivesBuildItem"},{"count":1,"class":"io.quarkus.deployment.BooleanSupplierFactoryBuildItem"},{"count":1,"class":"io.quarkus.deployment.builditem.ContextHandlerBuildItem"},{"count":1,"class":"io.quarkus.arc.deployment.TransformedAnnotationsBuildItem"},{"count":1,"class":"io.quarkus.deployment.builditem.GeneratedFileSystemResourceHandledBuildItem"},{"count":1,"class":"io.quarkus.deployment.builditem.DevServicesLauncherConfigResultBuildItem"},{"count":1,"class":"io.quarkus.deployment.pkg.builditem.OutputTargetBuildItem"},{"count":1,"class":"io.quarkus.smallrye.reactivemessaging.deployment.items.ChannelBuildItem"},{"count":1,"class":"io.quarkus.arc.deployment.PreBeanContainerBuildItem"},{"count":1,"class":"io.quarkus.arc.deployment.InjectionPointTransformerBuildItem"},{"count":1,"class":"io.quarkus.deployment.builditem.ThreadFactoryBuildItem"},{"count":1,"class":"io.quarkus.deployment.builditem.ApplicationIndexBuildItem"},{"count":1,"class":"io.quarkus.deployment.builditem.CombinedIndexBuildItem"},{"count":1,"class":"io.quarkus.deployment.Capabilities"},{"count":1,"class":"io.quarkus.arc.deployment.GeneratedBeanBuildItem"},{"count":1,"class":"io.quarkus.deployment.logging.LoggingSetupBuildItem"},{"count":1,"class":"io.quarkus.deployment.builditem.ExecutorBuildItem"},{"count":1,"class":"io.quarkus.arc.deployment.ArcContainerBuildItem"},{"count":1,"class":"io.quarkus.smallrye.context.deployment.spi.ThreadContextProviderBuildItem"},{"count":1,"class":"io.quarkus.arc.deployment.BeanRegistrationPhaseBuildItem"},{"count":1,"class":"io.quarkus.arc.deployment.ObserverRegistrationPhaseBuildItem"},{"count":1,"class":"io.quarkus.deployment.builditem.ApplicationClassNameBuildItem"},{"count":1,"class":"io.quarkus.deployment.builditem.nativeimage.NativeImageResourceBuildItem"},{"count":1,"class":"io.quarkus.deployment.dev.DisableInstrumentationForIndexPredicateBuildItem"},{"count":1,"class":"io.quarkus.vertx.deployment.VertxBuildItem"},{"count":1,"class":"io.quarkus.arc.deployment.BeanContainerBuildItem"},{"count":1,"class":"io.quarkus.arc.deployment.CurrentContextFactoryBuildItem"},{"count":1,"class":"io.quarkus.deployment.ide.EffectiveIdeBuildItem"},{"count":1,"class":"io.quarkus.deployment.pkg.builditem.CurateOutcomeBuildItem"},{"count":1,"class":"io.quarkus.deployment.builditem.ConfigurationBuildItem"},{"count":1,"class":"io.quarkus.deployment.steps.CapabilityAggregationStep$CapabilitiesConfiguredInDescriptorsBuildItem"},{"count":1,"class":"io.quarkus.deployment.builditem.ApplicationStartBuildItem"},{"count":1,"class":"io.quarkus.deployment.builditem.ApplicationClassPredicateBuildItem"},{"count":1,"class":"io.quarkus.deployment.builditem.LogCategoryMinLevelDefaultsBuildItem"},{"count":1,"class":"io.quarkus.deployment.builditem.GeneratedResourceBuildItem"},{"count":1,"class":"io.quarkus.arc.deployment.ContextRegistrationPhaseBuildItem"},{"count":1,"class":"io.quarkus.arc.deployment.CustomScopeAnnotationsBuildItem"},{"count":1,"class":"io.quarkus.deployment.builditem.IOThreadDetectorBuildItem"},{"count":1,"class":"io.quarkus.deployment.builditem.SslNativeConfigBuildItem"},{"count":1,"class":"io.quarkus.arc.deployment.AutoInjectAnnotationBuildItem"},{"count":1,"class":"io.quarkus.arc.deployment.CompletedApplicationClassPredicateBuildItem"},{"count":1,"class":"io.quarkus.deployment.builditem.ApplicationInfoBuildItem"},{"count":1,"class":"io.quarkus.deployment.ide.IdeRunningProcessBuildItem"},{"count":1,"class":"io.quarkus.deployment.builditem.LogCategoryBuildItem"},{"count":1,"class":"io.quarkus.deployment.ide.IdeFileBuildItem"},{"count":1,"class":"io.quarkus.deployment.builditem.MainClassBuildItem"},{"count":1,"class":"io.quarkus.smallrye.reactivemessaging.deployment.items.InjectedEmitterBuildItem"}],"itemsCount":867,"buildTarget":"SensorDataAdapter-1.0-SNAPSHOT"}